LICENSE
README.md
setup.cfg
setup.py
huggingfaceinference/__init__.py
huggingfaceinference/pipeline.py
huggingfaceinference.egg-info/PKG-INFO
huggingfaceinference.egg-info/SOURCES.txt
huggingfaceinference.egg-info/dependency_links.txt
huggingfaceinference.egg-info/not-zip-safe
huggingfaceinference.egg-info/requires.txt
huggingfaceinference.egg-info/top_level.txt