Metadata-Version: 2.1
Name: huggingfaceinference
Version: 0.9
Summary: Simple inference usecases using hugging transformers library on varied use cases of the AI/ML Domain
Home-page: https://github.com/Vishnunkumar/huggingfaceinference/
Author: Vishnu Nandakumar
Author-email: nkumarvishnu25@gmail.com
License: MIT license
Keywords: huggingfaceinference
Classifier: Development Status :: 3 - Alpha
Classifier: Intended Audience :: Developers
Classifier: Topic :: Software Development :: Build Tools
Classifier: License :: OSI Approved :: MIT License
Classifier: Programming Language :: Python :: 3
Classifier: Programming Language :: Python :: 3.4
Classifier: Programming Language :: Python :: 3.5
Classifier: Programming Language :: Python :: 3.6
License-File: LICENSE
